<?xml version='1.0' encoding='utf-8'?>
<document id="25106415"><sentence text="Clinical CYP3A inhibitor alternatives to ketoconazole, clarithromycin and itraconazole, are not transported into the liver by hepatic organic anion transporting polypeptides and organic cation transporter 1."><entity charOffset="41-53" id="DDI-PubMed.25106415.s1.e0" text="ketoconazole" /><entity charOffset="55-69" id="DDI-PubMed.25106415.s1.e1" text="clarithromycin" /><entity charOffset="74-86" id="DDI-PubMed.25106415.s1.e2" text="itraconazole" /><pair ddi="false" e1="DDI-PubMed.25106415.s1.e0" e2="DDI-PubMed.25106415.s1.e0" /><pair ddi="false" e1="DDI-PubMed.25106415.s1.e0" e2="DDI-PubMed.25106415.s1.e1" /><pair ddi="false" e1="DDI-PubMed.25106415.s1.e0" e2="DDI-PubMed.25106415.s1.e2" /><pair ddi="false" e1="DDI-PubMed.25106415.s1.e1" e2="DDI-PubMed.25106415.s1.e1" /><pair ddi="false" e1="DDI-PubMed.25106415.s1.e1" e2="DDI-PubMed.25106415.s1.e2" /></sentence><sentence text="Ketoconazole is no longer available for clinical determination of worst-case victim drug-drug interaction (DDI) potential for cytochrome P450 3A (CYP3A)-substrate drugs; clarithromycin and itraconazole are the proposed replacements"><entity charOffset="0-12" id="DDI-PubMed.25106415.s2.e0" text="Ketoconazole" /><entity charOffset="170-184" id="DDI-PubMed.25106415.s2.e1" text="clarithromycin" /><entity charOffset="189-201" id="DDI-PubMed.25106415.s2.e2" text="itraconazole" /><pair ddi="false" e1="DDI-PubMed.25106415.s2.e0" e2="DDI-PubMed.25106415.s2.e0" /><pair ddi="false" e1="DDI-PubMed.25106415.s2.e0" e2="DDI-PubMed.25106415.s2.e1" /><pair ddi="false" e1="DDI-PubMed.25106415.s2.e0" e2="DDI-PubMed.25106415.s2.e2" /><pair ddi="false" e1="DDI-PubMed.25106415.s2.e1" e2="DDI-PubMed.25106415.s2.e1" /><pair ddi="false" e1="DDI-PubMed.25106415.s2.e1" e2="DDI-PubMed.25106415.s2.e2" /></sentence><sentence text=" Ketoconazole DDIs are described by unbound systemic exposures due to absence of carrier-facilitated hepatic uptake, but this aspect of clarithromycin and itraconazole disposition has not been investigated"><entity charOffset="1-13" id="DDI-PubMed.25106415.s3.e0" text="Ketoconazole" /><entity charOffset="136-150" id="DDI-PubMed.25106415.s3.e1" text="clarithromycin" /><entity charOffset="155-167" id="DDI-PubMed.25106415.s3.e2" text="itraconazole" /><pair ddi="false" e1="DDI-PubMed.25106415.s3.e0" e2="DDI-PubMed.25106415.s3.e0" /><pair ddi="false" e1="DDI-PubMed.25106415.s3.e0" e2="DDI-PubMed.25106415.s3.e1" /><pair ddi="false" e1="DDI-PubMed.25106415.s3.e0" e2="DDI-PubMed.25106415.s3.e2" /><pair ddi="false" e1="DDI-PubMed.25106415.s3.e1" e2="DDI-PubMed.25106415.s3.e1" /><pair ddi="false" e1="DDI-PubMed.25106415.s3.e1" e2="DDI-PubMed.25106415.s3.e2" /></sentence><sentence text=" At present, transport of clarithromycin, itraconazole, and hydroxyitraconazole by hepatic organic anion transporting polypeptides (OATPs) and organic cation transporter 1 (OCT1) was examined in vitro and in vivo"><entity charOffset="26-40" id="DDI-PubMed.25106415.s4.e0" text="clarithromycin" /><entity charOffset="42-54" id="DDI-PubMed.25106415.s4.e1" text="itraconazole" /><entity charOffset="60-79" id="DDI-PubMed.25106415.s4.e2" text="hydroxyitraconazole" /><pair ddi="false" e1="DDI-PubMed.25106415.s4.e0" e2="DDI-PubMed.25106415.s4.e0" /><pair ddi="false" e1="DDI-PubMed.25106415.s4.e0" e2="DDI-PubMed.25106415.s4.e1" /><pair ddi="false" e1="DDI-PubMed.25106415.s4.e0" e2="DDI-PubMed.25106415.s4.e2" /><pair ddi="false" e1="DDI-PubMed.25106415.s4.e1" e2="DDI-PubMed.25106415.s4.e1" /><pair ddi="false" e1="DDI-PubMed.25106415.s4.e1" e2="DDI-PubMed.25106415.s4.e2" /></sentence><sentence text=" As for ketoconazole, uptake of clarithromycin, itraconazole, and hydroxyitraconazole into OATP1B1, OATP1B3, OATP2B1, and OCT1 expressing human embryonic kidney 293 (HEK293) cells was not greater than in vector controls"><entity charOffset="8-20" id="DDI-PubMed.25106415.s5.e0" text="ketoconazole" /><entity charOffset="32-46" id="DDI-PubMed.25106415.s5.e1" text="clarithromycin" /><entity charOffset="48-60" id="DDI-PubMed.25106415.s5.e2" text="itraconazole" /><entity charOffset="66-85" id="DDI-PubMed.25106415.s5.e3" text="hydroxyitraconazole" /><pair ddi="false" e1="DDI-PubMed.25106415.s5.e0" e2="DDI-PubMed.25106415.s5.e0" /><pair ddi="false" e1="DDI-PubMed.25106415.s5.e0" e2="DDI-PubMed.25106415.s5.e1" /><pair ddi="false" e1="DDI-PubMed.25106415.s5.e0" e2="DDI-PubMed.25106415.s5.e2" /><pair ddi="false" e1="DDI-PubMed.25106415.s5.e0" e2="DDI-PubMed.25106415.s5.e3" /><pair ddi="false" e1="DDI-PubMed.25106415.s5.e1" e2="DDI-PubMed.25106415.s5.e1" /><pair ddi="false" e1="DDI-PubMed.25106415.s5.e1" e2="DDI-PubMed.25106415.s5.e2" /><pair ddi="false" e1="DDI-PubMed.25106415.s5.e1" e2="DDI-PubMed.25106415.s5.e3" /><pair ddi="false" e1="DDI-PubMed.25106415.s5.e2" e2="DDI-PubMed.25106415.s5.e2" /><pair ddi="false" e1="DDI-PubMed.25106415.s5.e2" e2="DDI-PubMed.25106415.s5.e3" /></sentence><sentence text=" Uptake into these HEK293 cells and human hepatocytes was not impaired by the prototypical OATP, OCT, and sodium/taurocholate cotransporting polypeptide inhibitors bromosulfophthalein, imipramine, and taurocholate, respectively"><entity charOffset="106-112" id="DDI-PubMed.25106415.s6.e0" text="sodium" /><entity charOffset="113-125" id="DDI-PubMed.25106415.s6.e1" text="taurocholate" /><entity charOffset="164-183" id="DDI-PubMed.25106415.s6.e2" text="bromosulfophthalein" /><entity charOffset="185-195" id="DDI-PubMed.25106415.s6.e3" text="imipramine" /><entity charOffset="201-213" id="DDI-PubMed.25106415.s6.e4" text="taurocholate" /><pair ddi="false" e1="DDI-PubMed.25106415.s6.e0" e2="DDI-PubMed.25106415.s6.e0" /><pair ddi="false" e1="DDI-PubMed.25106415.s6.e0" e2="DDI-PubMed.25106415.s6.e1" /><pair ddi="false" e1="DDI-PubMed.25106415.s6.e0" e2="DDI-PubMed.25106415.s6.e2" /><pair ddi="false" e1="DDI-PubMed.25106415.s6.e0" e2="DDI-PubMed.25106415.s6.e3" /><pair ddi="false" e1="DDI-PubMed.25106415.s6.e0" e2="DDI-PubMed.25106415.s6.e4" /><pair ddi="false" e1="DDI-PubMed.25106415.s6.e1" e2="DDI-PubMed.25106415.s6.e1" /><pair ddi="false" e1="DDI-PubMed.25106415.s6.e1" e2="DDI-PubMed.25106415.s6.e2" /><pair ddi="false" e1="DDI-PubMed.25106415.s6.e1" e2="DDI-PubMed.25106415.s6.e3" /><pair ddi="false" e1="DDI-PubMed.25106415.s6.e1" e2="DDI-PubMed.25106415.s6.e4" /><pair ddi="false" e1="DDI-PubMed.25106415.s6.e2" e2="DDI-PubMed.25106415.s6.e2" /><pair ddi="false" e1="DDI-PubMed.25106415.s6.e2" e2="DDI-PubMed.25106415.s6.e3" /><pair ddi="false" e1="DDI-PubMed.25106415.s6.e2" e2="DDI-PubMed.25106415.s6.e4" /><pair ddi="false" e1="DDI-PubMed.25106415.s6.e3" e2="DDI-PubMed.25106415.s6.e3" /><pair ddi="false" e1="DDI-PubMed.25106415.s6.e3" e2="DDI-PubMed.25106415.s6.e4" /></sentence><sentence text=" In contrast, uptake of the positive controls, atorvastatin for OATPs and metformin for OCT1, was significantly enhanced by relevant transporter expression, and uptake into both these HEK293 cells and human hepatocytes was significantly impaired by prototypical inhibitors"><entity charOffset="47-59" id="DDI-PubMed.25106415.s7.e0" text="atorvastatin" /><entity charOffset="64-69" id="DDI-PubMed.25106415.s7.e1" text="OATPs" /><entity charOffset="74-83" id="DDI-PubMed.25106415.s7.e2" text="metformin" /><pair ddi="false" e1="DDI-PubMed.25106415.s7.e0" e2="DDI-PubMed.25106415.s7.e0" /><pair ddi="false" e1="DDI-PubMed.25106415.s7.e0" e2="DDI-PubMed.25106415.s7.e1" /><pair ddi="false" e1="DDI-PubMed.25106415.s7.e0" e2="DDI-PubMed.25106415.s7.e2" /><pair ddi="false" e1="DDI-PubMed.25106415.s7.e1" e2="DDI-PubMed.25106415.s7.e1" /><pair ddi="false" e1="DDI-PubMed.25106415.s7.e1" e2="DDI-PubMed.25106415.s7.e2" /></sentence><sentence text=" In Oatp1a/1b gene cluster knockout mice, which lack the major hepatic Oatps, and in Oct1/2 knockout mice, ketoconazole, clarithromycin, itraconazole, and hydroxyitraconazole oral exposure was not increased, and the liver-to-blood partition coefficient (Kp) was not decreased"><entity charOffset="107-119" id="DDI-PubMed.25106415.s8.e0" text="ketoconazole" /><entity charOffset="121-135" id="DDI-PubMed.25106415.s8.e1" text="clarithromycin" /><entity charOffset="137-149" id="DDI-PubMed.25106415.s8.e2" text="itraconazole" /><entity charOffset="155-174" id="DDI-PubMed.25106415.s8.e3" text="hydroxyitraconazole" /><pair ddi="false" e1="DDI-PubMed.25106415.s8.e0" e2="DDI-PubMed.25106415.s8.e0" /><pair ddi="false" e1="DDI-PubMed.25106415.s8.e0" e2="DDI-PubMed.25106415.s8.e1" /><pair ddi="false" e1="DDI-PubMed.25106415.s8.e0" e2="DDI-PubMed.25106415.s8.e2" /><pair ddi="false" e1="DDI-PubMed.25106415.s8.e0" e2="DDI-PubMed.25106415.s8.e3" /><pair ddi="false" e1="DDI-PubMed.25106415.s8.e1" e2="DDI-PubMed.25106415.s8.e1" /><pair ddi="false" e1="DDI-PubMed.25106415.s8.e1" e2="DDI-PubMed.25106415.s8.e2" /><pair ddi="false" e1="DDI-PubMed.25106415.s8.e1" e2="DDI-PubMed.25106415.s8.e3" /><pair ddi="false" e1="DDI-PubMed.25106415.s8.e2" e2="DDI-PubMed.25106415.s8.e2" /><pair ddi="false" e1="DDI-PubMed.25106415.s8.e2" e2="DDI-PubMed.25106415.s8.e3" /></sentence><sentence text=" By contrast relative to wild-type mice, in Oatp1a/1b- and Oct1/2-knockout mice, atorvastatin and metformin oral exposure was significantly increased, and liver Kp was significantly decreased"><entity charOffset="81-93" id="DDI-PubMed.25106415.s9.e0" text="atorvastatin" /><entity charOffset="98-107" id="DDI-PubMed.25106415.s9.e1" text="metformin" /><pair ddi="false" e1="DDI-PubMed.25106415.s9.e0" e2="DDI-PubMed.25106415.s9.e0" /><pair ddi="false" e1="DDI-PubMed.25106415.s9.e0" e2="DDI-PubMed.25106415.s9.e1" /></sentence><sentence text=" The present studies provide in vitro and in vivo evidence that, like ketoconazole, clarithromycin, itraconazole, and hydroxyitraconazole are not transported into the liver by hepatic uptake transporters, including OATPs and OCT1"><entity charOffset="70-82" id="DDI-PubMed.25106415.s10.e0" text="ketoconazole" /><entity charOffset="84-98" id="DDI-PubMed.25106415.s10.e1" text="clarithromycin" /><entity charOffset="100-112" id="DDI-PubMed.25106415.s10.e2" text="itraconazole" /><entity charOffset="118-137" id="DDI-PubMed.25106415.s10.e3" text="hydroxyitraconazole" /><entity charOffset="215-233" id="DDI-PubMed.25106415.s10.e4" text="OATPs" /><pair ddi="false" e1="DDI-PubMed.25106415.s10.e0" e2="DDI-PubMed.25106415.s10.e0" /><pair ddi="false" e1="DDI-PubMed.25106415.s10.e0" e2="DDI-PubMed.25106415.s10.e1" /><pair ddi="false" e1="DDI-PubMed.25106415.s10.e0" e2="DDI-PubMed.25106415.s10.e2" /><pair ddi="false" e1="DDI-PubMed.25106415.s10.e0" e2="DDI-PubMed.25106415.s10.e3" /><pair ddi="false" e1="DDI-PubMed.25106415.s10.e0" e2="DDI-PubMed.25106415.s10.e4" /><pair ddi="false" e1="DDI-PubMed.25106415.s10.e1" e2="DDI-PubMed.25106415.s10.e1" /><pair ddi="false" e1="DDI-PubMed.25106415.s10.e1" e2="DDI-PubMed.25106415.s10.e2" /><pair ddi="false" e1="DDI-PubMed.25106415.s10.e1" e2="DDI-PubMed.25106415.s10.e3" /><pair ddi="false" e1="DDI-PubMed.25106415.s10.e1" e2="DDI-PubMed.25106415.s10.e4" /><pair ddi="false" e1="DDI-PubMed.25106415.s10.e2" e2="DDI-PubMed.25106415.s10.e2" /><pair ddi="false" e1="DDI-PubMed.25106415.s10.e2" e2="DDI-PubMed.25106415.s10.e3" /><pair ddi="false" e1="DDI-PubMed.25106415.s10.e2" e2="DDI-PubMed.25106415.s10.e4" /><pair ddi="false" e1="DDI-PubMed.25106415.s10.e3" e2="DDI-PubMed.25106415.s10.e3" /><pair ddi="false" e1="DDI-PubMed.25106415.s10.e3" e2="DDI-PubMed.25106415.s10.e4" /></sentence><sentence text="" /></document>