<?xml version='1.0' encoding='utf-8'?>
<document id="26257936"><sentence text="Possible drug-drug interaction in dogs and cats resulted from alteration in drug metabolism: A mini review." /><sentence text="Pharmacokinetic drug-drug interactions (in particular at metabolism) may result in fatal adverse effects in some cases" /><sentence text=" This basic information, therefore, is needed for drug therapy even in veterinary medicine, as multidrug therapy is not rare in canines and felines" /><sentence text=" The aim of this review was focused on possible drug-drug interactions in dogs and cats" /><sentence text=" The interaction includes enzyme induction by phenobarbital, enzyme inhibition by ketoconazole and fluoroquinolones, and down-regulation of enzymes by dexamethasone"><entity charOffset="82-94" id="DDI-PubMed.26257936.s5.e0" text="ketoconazole" /><entity charOffset="151-164" id="DDI-PubMed.26257936.s5.e1" text="dexamethasone" /><pair ddi="false" e1="DDI-PubMed.26257936.s5.e0" e2="DDI-PubMed.26257936.s5.e0" /><pair ddi="false" e1="DDI-PubMed.26257936.s5.e0" e2="DDI-PubMed.26257936.s5.e1" /></sentence><sentence text=" A final conclusion based upon the available literatures and author's experience is given at the end of the review" /><sentence text=" " /></document>