<?xml version='1.0' encoding='utf-8'?>
<document id="26456671"><sentence text="Human hepatoma cell lines on gas foaming templated alginate scaffolds for in vitro drug-drug interaction and metabolism studies." /><sentence text="Liver in vitro systems that allow reliable prediction of major human in vivo metabolic pathways have a significant impact in drug screening and drug metabolism research" /><sentence text=" In the present study, a novel porous scaffold composed of alginate was prepared by employing a gas-in-liquid foaming approach" /><sentence text=" Galactose residues were introduced on scaffold surfaces to promote cell adhesion and to enhance liver specific functions of the entrapped HepG2/C3A cells"><entity charOffset="1-10" id="DDI-PubMed.26456671.s4.e0" text="Galactose" /></sentence><sentence text=" Hepatoma cells in the gal-alginate scaffold showed higher levels of liver specific products (albumin and urea) and were more responsive to specific inducers (e"><entity charOffset="106-110" id="DDI-PubMed.26456671.s5.e0" text="urea" /></sentence><sentence text="g" /><sentence text=" dexamethasone) and inhibitors (e"><entity charOffset="1-14" id="DDI-PubMed.26456671.s7.e0" text="dexamethasone" /></sentence><sentence text="g" /><sentence text=" ketoconazole) of the CYP3A4 system than in conventional monolayer culture"><entity charOffset="1-13" id="DDI-PubMed.26456671.s9.e0" text="ketoconazole" /></sentence><sentence text=" HepG2/C3A cells were also more efficient in terms of rapid elimination of testosterone, used as a model substance, at rates comparable to those of in vivo excretion"><entity charOffset="75-87" id="DDI-PubMed.26456671.s10.e0" text="testosterone" /></sentence><sentence text=" In addition, an improvement in metabolism of testosterone, in terms of phase II metabolite formation, was also observed when the more differentiated HepaRG cells were used"><entity charOffset="46-58" id="DDI-PubMed.26456671.s11.e0" text="testosterone" /></sentence><sentence text=" Together the data suggest that hepatocyte/gas templated alginate-systems provide an innovative high throughput platform for in vitro drug metabolism and drug-drug interaction studies, with broad fields of application, and might provide a valid tool for minimizing animal use in preclinical testing of human relevance" /><sentence text=" " /></document>